{
  "toolName": "BackupGuard",
  "toolId": "backupguard",
  "subdomain": "backupguard.maula.ai",
  "mainDomain": "maula.ai",
  "aiAssistant": {
    "name": "Maula AI - BackupGuard Assistant",
    "path": "/maula/ai",
    "fullUrl": "https://backupguard.maula.ai/maula/ai",
    "systemPrompt": "You are Maula AI, an enterprise backup security expert specializing in data protection, disaster recovery, ransomware defense, and backup integrity validation. Help users with: backup job scheduling (full, incremental, differential), 3-2-1 backup strategy implementation, ransomware detection and recovery, immutable snapshot management, compliance reporting (SOX, HIPAA, GDPR), restore testing automation, RTO/RPO optimization, storage lifecycle management, and backup best practices. Provide guidance on Veeam, Commvault, VMware backups, cloud backup (AWS S3, Azure Blob), air-gap strategies, and disaster recovery planning."
  },
  "ports": {
    "frontend": 3044,
    "api": 4044,
    "ml": 8044,
    "websocket": 6044
  },
  "database": {
    "name": "backupguard_db",
    "collections": ["backupjobs", "snapshots", "storagepools", "integritychecks", "ransomwarealerts", "compliancereports", "accesslogs", "alerts"]
  },
  "theme": {
    "primary": "#0EA5E9",
    "secondary": "#06B6D4",
    "accent": "#6366F1",
    "dark": "#0F172A",
    "darker": "#020617",
    "gradient": "linear-gradient(135deg, #0EA5E9 0%, #06B6D4 100%)",
    "description": "Blue/cyan data protection theme representing trust, security, and data integrity"
  },
  "features": [
    "Automated backup job orchestration",
    "Ransomware detection & prevention",
    "Immutable backup snapshots (WORM)",
    "Backup integrity validation & testing",
    "Disaster recovery automation",
    "RTO/RPO monitoring",
    "Compliance reporting (SOX, HIPAA, GDPR, PCI-DSS)",
    "Storage lifecycle management",
    "Air-gap backup validation",
    "ML-powered anomaly detection"
  ],
  "integrations": [
    "Veeam Backup & Replication",
    "Commvault Complete Backup",
    "VMware vSphere",
    "Microsoft Hyper-V",
    "AWS S3 & Glacier",
    "Azure Blob Storage",
    "Google Cloud Storage",
    "Dell EMC Data Domain",
    "NetApp SnapVault"
  ],
  "keyMetrics": [
    "Total Backup Capacity (PB)",
    "Active Backup Jobs",
    "Ransomware Threats Blocked",
    "Compliance Score (0-100)",
    "Backup Success Rate (%)",
    "RTO/RPO Achievement (%)",
    "Storage Deduplication Ratio",
    "Integrity Validation Pass Rate (%)"
  ]
}
